chercher_plugin_pdf/__init__.py
chercher_plugin_pdf-0.1.6.dist-info/licenses/LICENSE
chercher_plugin_pdf-0.1.6.dist-info/METADATA
chercher_plugin_pdf-0.1.6.dist-info/WHEEL
chercher_plugin_pdf-0.1.6.dist-info/entry_points.txt
chercher_plugin_pdf-0.1.6.dist-info/top_level.txt
chercher_plugin_pdf-0.1.6.dist-info/RECORD
